async_easy_model/__init__.py
async_easy_model/auto_relationships.py
async_easy_model/compat.py
async_easy_model/compat.pyi
async_easy_model/migrations.py
async_easy_model/model.py
async_easy_model/py.typed
async_easy_model/relationships.py
async_easy_model/visualization.py
async_easy_model-0.4.3.dist-info/licenses/LICENSE
async_easy_model-0.4.3.dist-info/METADATA
async_easy_model-0.4.3.dist-info/WHEEL
async_easy_model-0.4.3.dist-info/top_level.txt
async_easy_model-0.4.3.dist-info/RECORD
