Metadata-Version: 2.4
Name: async-easy-model
Version: 0.4.3
Summary: A simplified SQLModel-based ORM for async database operations
Home-page: https://github.com/puntorigen/easy-model
Author: Pablo Schaffner
Author-email: pablo@puntorigen.com
Keywords: orm,sqlmodel,database,async,postgresql,sqlite,mysql
Classifier: Development Status :: 3 - Alpha
Classifier: Intended Audience :: Developers
Classifier: License :: OSI Approved :: MIT License
Classifier: Operating System :: OS Independent
Classifier: Programming Language :: Python :: 3
Classifier: Programming Language :: Python :: 3.7
Classifier: Programming Language :: Python :: 3.8
Classifier: Programming Language :: Python :: 3.9
Classifier: Programming Language :: Python :: 3.10
Classifier: Programming Language :: Python :: 3.11
Requires-Python: >=3.7
License-File: LICENSE
Requires-Dist: sqlmodel>=0.0.8
Requires-Dist: sqlalchemy>=2.0.0
Requires-Dist: asyncpg>=0.25.0
Requires-Dist: aiosqlite>=0.19.0
Requires-Dist: aiomysql>=0.1.1
Requires-Dist: greenlet>=3.1.1
Requires-Dist: inflection>=0.5.1
Dynamic: author
Dynamic: author-email
Dynamic: classifier
Dynamic: description
Dynamic: description-content-type
Dynamic: home-page
Dynamic: keywords
Dynamic: license-file
Dynamic: requires-dist
Dynamic: requires-python
Dynamic: summary
